<?xml version="1.0" encoding="UTF-8"?>
<typeSystemDescription xmlns="http://uima.apache.org/resourceSpecifier">
  <name>UIMA.Ext.Tokenizer type system</name>
  <description/>
  <version>1.0</version>
  <vendor/>
  <types>
    <typeDescription>
      <name>ru.kfu.cll.uima.segmentation.fstype.TokenBase</name>
      <description/>
      <supertypeName>uima.tcas.Annotation</supertypeName>
    </typeDescription>
    <typeDescription>
      <name>ru.kfu.cll.uima.segmentation.fstype.Token</name>
      <description/>
      <supertypeName>ru.kfu.cll.uima.segmentation.fstype.TokenBase</supertypeName>
      <features>
				<featureDescription>
					<name>TypeName</name>
					<description></description>
					<rangeTypeName>uima.cas.String</rangeTypeName>
					<!-- <elementType>[Name]</elementType> -->
					<!-- <multipleReferencesAllowed>true</multipleReferencesAllowed> -->
				</featureDescription>
       </features>
      
      
    </typeDescription>
    <typeDescription>
      <name>ru.kfu.cll.uima.segmentation.fstype.WhiteSpace</name>
      <description/>
      <supertypeName>ru.kfu.cll.uima.segmentation.fstype.TokenBase</supertypeName>
    </typeDescription>
    <typeDescription>
      <name>ru.kfu.cll.uima.segmentation.fstype.W</name>
      <description/>
      <supertypeName>ru.kfu.cll.uima.segmentation.fstype.Token</supertypeName>
    </typeDescription>
    <typeDescription>
      <name>ru.kfu.cll.uima.segmentation.fstype.CW</name>
      <description/>
      <supertypeName>ru.kfu.cll.uima.segmentation.fstype.W</supertypeName>
    </typeDescription>
    <typeDescription>
      <name>ru.kfu.cll.uima.segmentation.fstype.SW</name>
      <description/>
      <supertypeName>ru.kfu.cll.uima.segmentation.fstype.W</supertypeName>
    </typeDescription>
    <typeDescription>
      <name>ru.kfu.cll.uima.segmentation.fstype.CAP</name>
      <description/>
      <supertypeName>ru.kfu.cll.uima.segmentation.fstype.CW</supertypeName>
    </typeDescription>
    <typeDescription>
      <name>ru.kfu.cll.uima.segmentation.fstype.PM</name>
      <description/>
      <supertypeName>ru.kfu.cll.uima.segmentation.fstype.Token</supertypeName>
    </typeDescription>
    <typeDescription>
      <name>ru.kfu.cll.uima.segmentation.fstype.COLON</name>
      <description/>
      <supertypeName>ru.kfu.cll.uima.segmentation.fstype.PM</supertypeName>
    </typeDescription>
    <typeDescription>
      <name>ru.kfu.cll.uima.segmentation.fstype.PERIOD</name>
      <description/>
      <supertypeName>ru.kfu.cll.uima.segmentation.fstype.PM</supertypeName>
    </typeDescription>
    <typeDescription>
      <name>ru.kfu.cll.uima.segmentation.fstype.QUESTION</name>
      <description/>
      <supertypeName>ru.kfu.cll.uima.segmentation.fstype.PM</supertypeName>
    </typeDescription>
    <typeDescription>
      <name>ru.kfu.cll.uima.segmentation.fstype.EXCLAMATION</name>
      <description/>
      <supertypeName>ru.kfu.cll.uima.segmentation.fstype.PM</supertypeName>
    </typeDescription>
    <typeDescription>
      <name>ru.kfu.cll.uima.segmentation.fstype.COMMA</name>
      <description/>
      <supertypeName>ru.kfu.cll.uima.segmentation.fstype.PM</supertypeName>
    </typeDescription>
    <typeDescription>
      <name>ru.kfu.cll.uima.segmentation.fstype.SEMICOLON</name>
      <description/>
      <supertypeName>ru.kfu.cll.uima.segmentation.fstype.PM</supertypeName>
    </typeDescription>
    <typeDescription>
      <name>ru.kfu.cll.uima.segmentation.fstype.NUM</name>
      <description/>
      <supertypeName>ru.kfu.cll.uima.segmentation.fstype.Token</supertypeName>
    </typeDescription>
    <typeDescription>
      <name>ru.kfu.cll.uima.segmentation.fstype.SPECIAL</name>
      <description/>
      <supertypeName>ru.kfu.cll.uima.segmentation.fstype.Token</supertypeName>
    </typeDescription>
    <typeDescription>
      <name>ru.kfu.cll.uima.segmentation.fstype.SPACE</name>
      <description/>
      <supertypeName>ru.kfu.cll.uima.segmentation.fstype.WhiteSpace</supertypeName>
    </typeDescription>
    <typeDescription>
      <name>ru.kfu.cll.uima.segmentation.fstype.BREAK</name>
      <description/>
      <supertypeName>ru.kfu.cll.uima.segmentation.fstype.WhiteSpace</supertypeName>
    </typeDescription>
    <typeDescription>
      <name>ru.kfu.cll.uima.segmentation.fstype.NBSP</name>
      <description/>
      <supertypeName>ru.kfu.cll.uima.segmentation.fstype.WhiteSpace</supertypeName>
    </typeDescription>
  </types>
</typeSystemDescription>